jmath/__init__.py
jmath/autodiff.py
jmath/complex.py
jmath/discrete.py
jmath/exceptions.py
jmath/modular.py
jmath/uncertainties.py
jmath/abstract/__init__.py
jmath/abstract/heaps.py
jmath/abstract/lists.py
jmath/abstract/queues.py
jmath/abstract/stacks.py
jmath/approximation/__init__.py
jmath/approximation/differentiation.py
jmath/approximation/euler_method.py
jmath/approximation/integration.py
jmath/approximation/newton_method.py
jmath/cryptography/__init__.py
jmath/cryptography/affine.py
jmath/cryptography/tools.py
jmath/graphics/__init__.py
jmath/graphics/shapes.py
jmath/graphics/windows.py
jmath/linearalgebra/__init__.py
jmath/linearalgebra/lines.py
jmath/linearalgebra/planes.py
jmath/linearalgebra/vectors.py
jmath/loud/__init__.py
jmath/loud/graphs.py
jmath/loud/modular.py
jmath/loud/primes.py
jmath/physics/__init__.py
jmath/physics/circuits.py
jmath/physics/mechanics.py
jmath/physics/prefixes.py
jmath/physics/simulation.py
jmath/units/__init__.py
jmath/units/annotation.py
jmath/units/conversion.py
jmath/units/other.py
jmath/units/si.py
jmath/units/units.py
jmath/universal/__init__.py
jmath/universal/hyperbolic.py
jmath/universal/logarithms.py
jmath/universal/natural.py
jmath/universal/tools.py
jmath/universal/trigonometry.py
jmath-4.4.1.dist-info/LICENSE
jmath-4.4.1.dist-info/METADATA
jmath-4.4.1.dist-info/WHEEL
jmath-4.4.1.dist-info/top_level.txt
jmath-4.4.1.dist-info/RECORD
