Metadata-Version: 2.1
Name: jmath
Version: 4.4.1
Summary: Mathematics Tools
Home-page: https://github.com/JHay0112/jmath
Author: Jordan Hay
License: MIT
Project-URL: Bug Tracker, https://github.com/JHay0112/jmath/issues
Platform: UNKNOWN
Classifier: Programming Language :: Python :: 3
Classifier: License :: OSI Approved :: MIT License
Classifier: Operating System :: OS Independent
Requires-Python: >=3.6
License-File: LICENSE
